sai_airflow_plugins/__init__.py
sai_airflow_plugins/hooks/__init__.py
sai_airflow_plugins/hooks/fabric_hook.py
sai_airflow_plugins/hooks/mattermost_webhook_hook.py
sai_airflow_plugins/operators/__init__.py
sai_airflow_plugins/operators/conditional_operators.py
sai_airflow_plugins/operators/conditional_skip_mixin.py
sai_airflow_plugins/operators/fabric_operator.py
sai_airflow_plugins/operators/mattermost_webhook_operator.py
sai_airflow_plugins/sensors/__init__.py
sai_airflow_plugins/sensors/conditional_sensors.py
sai_airflow_plugins/sensors/fabric_sensor.py
tests/__init__.py
tests/mocked_fabric_hook.py
tests/test_conditional_skip_mixin.py
tests/test_fabric_hook.py
tests/test_fabric_operator.py
tests/test_fabric_sensor.py
tests/test_mattermost_webhook_hook.py
tests/test_mattermost_webhook_operator.py
sai_airflow_plugins-0.2.1.dist-info/LICENSE
sai_airflow_plugins-0.2.1.dist-info/METADATA
sai_airflow_plugins-0.2.1.dist-info/WHEEL
sai_airflow_plugins-0.2.1.dist-info/top_level.txt
sai_airflow_plugins-0.2.1.dist-info/RECORD
