Metadata-Version: 2.1
Name: sai-airflow-plugins
Version: 0.2.1
Summary: A Python package with various operators, hooks and utilities for Apache Airflow
Home-page: https://github.com/Slimmer-AI/sai-airflow-plugins
Author: Slimmer.AI
License: Apache License 2.0
Classifier: Development Status :: 5 - Production/Stable
Classifier: Environment :: Plugins
Classifier: Programming Language :: Python :: 3.8
Classifier: Programming Language :: Python :: 3.9
Classifier: Programming Language :: Python :: 3.10
Classifier: Programming Language :: Python :: 3.11
Classifier: License :: OSI Approved :: Apache Software License
Classifier: Topic :: System :: Monitoring
License-File: LICENSE
Requires-Dist: apache-airflow[ssh] (>=1.10)
Requires-Dist: fabric (>=2.5)
Provides-Extra: docs
Requires-Dist: sphinx (<6,>=5) ; extra == 'docs'
Requires-Dist: sphinx-rtd-theme ; extra == 'docs'
Requires-Dist: sphinx-autodoc-typehints ; extra == 'docs'
Requires-Dist: sphinx-versions (==1.0.1) ; extra == 'docs'
Requires-Dist: click (<8) ; extra == 'docs'
Provides-Extra: tests
Requires-Dist: pytest ; extra == 'tests'
Requires-Dist: faker ; extra == 'tests'
